tests/__init__.py
tests/test_areas.py
tests/test_fields.py
tests/test_iterations.py
tests/test_projects.py
tests/test_testplan.py
tests/test_vstsclient.py
vstsclient/__init__.py
vstsclient/_auth.py
vstsclient/_conversion.py
vstsclient/_deserialize.py
vstsclient/_error.py
vstsclient/_hosts.py
vstsclient/constants.py
vstsclient/models.py
vstsclient/vstsclient.py
vstsclient/_http/__init__.py
vstsclient/_http/httpclient.py
vsts_client-1.2.1.dist-info/LICENSE
vsts_client-1.2.1.dist-info/METADATA
vsts_client-1.2.1.dist-info/WHEEL
vsts_client-1.2.1.dist-info/top_level.txt
vsts_client-1.2.1.dist-info/RECORD
